AegeanTools/AeRes.py
AegeanTools/BANE.py
AegeanTools/MIMAS.py
AegeanTools/__init__.py
AegeanTools/angle_tools.py
AegeanTools/catalogs.py
AegeanTools/cluster.py
AegeanTools/exceptions.py
AegeanTools/fits_tools.py
AegeanTools/fitting.py
AegeanTools/flags.py
AegeanTools/logging.py
AegeanTools/models.py
AegeanTools/msq2.py
AegeanTools/regions.py
AegeanTools/source_finder.py
AegeanTools/wcs_helpers.py
AegeanTools/CLI/AeReg.py
AegeanTools/CLI/AeRes.py
AegeanTools/CLI/BANE.py
AegeanTools/CLI/MIMAS.py
AegeanTools/CLI/SR6.py
AegeanTools/CLI/__init__.py
AegeanTools/CLI/aegean.py
AegeanTools/data/MOC.fits
aegeantools-2.3.5.data/scripts/fix_beam.py
aegeantools-2.3.5.dist-info/licenses/LICENSE
aegeantools-2.3.5.dist-info/METADATA
aegeantools-2.3.5.dist-info/WHEEL
aegeantools-2.3.5.dist-info/entry_points.txt
aegeantools-2.3.5.dist-info/top_level.txt
aegeantools-2.3.5.dist-info/RECORD
