Metadata-Version: 2.4
Name: AegeanTools
Version: 2.3.5
Author-email: Paul Hancock <Mr.Paul.Hancock@gmail.com>
License: Licensed under the [Academic Free License](https://opensource.org/licenses/AFL-3.0) version 3.0
Project-URL: Repository, https://github.com/PaulHancock/Aegean
Project-URL: Documentation, http://aegeantools.rtfd.io/
Project-URL: Issues, https://github.com/PaulHancock/Aegean/issues
Project-URL: Changelog, https://github.com/PaulHancock/Aegean/blob/main/CHANGELOG.md
Keywords: image processing,radioastronomy
Classifier: Development Status :: 5 - Production/Stable
Classifier: Intended Audience :: Science/Research
Classifier: Topic :: Scientific/Engineering :: Astronomy
Classifier: License :: OSI Approved :: Academic Free License (AFL)
Classifier: Programming Language :: Python :: 3.10
Classifier: Programming Language :: Python :: 3.11
Classifier: Programming Language :: Python :: 3.12
Classifier: Programming Language :: Python :: 3.13
Requires-Python: >=3.10
License-File: LICENSE
Requires-Dist: scipy>=1.11
Requires-Dist: tqdm>=4.67
Requires-Dist: numpy>=2.0
Requires-Dist: astropy>=6.1
Requires-Dist: healpy>=1.18
Requires-Dist: lmfit>=1.3
Requires-Dist: scikit-learn>=1.7
Requires-Dist: configargparse>=1.7
Provides-Extra: fast
Requires-Dist: numba>=0.60.0; extra == "fast"
Provides-Extra: faster
Requires-Dist: AegeanTools[fast]; extra == "faster"
Requires-Dist: mpi4py>=4.1; extra == "faster"
Provides-Extra: dev
Requires-Dist: pytest; extra == "dev"
Dynamic: license-file
